LICENSE
factopy/__init__.py
factopy/pca.py
factopy/svd.py
factopy-0.1.1.dist-info/LICENSE
factopy-0.1.1.dist-info/WHEEL
factopy-0.1.1.dist-info/METADATA
factopy-0.1.1.dist-info/RECORD
